UnitConvertChay/UnitConvertChay.py
UnitConvertChay/__init__.py
UnitConvertChay-1.0.0.dist-info/LICENSE
UnitConvertChay-1.0.0.dist-info/METADATA
UnitConvertChay-1.0.0.dist-info/WHEEL
UnitConvertChay-1.0.0.dist-info/top_level.txt
UnitConvertChay-1.0.0.dist-info/RECORD
