Metadata-Version: 2.1
Name: UnitConvertChay
Version: 1.0.0
Summary: A simple converter and a Physical quantity calculator.
Home-page: https://github.com/lichenyichay/Unit-Convert-Including/
Author: Chay
Author-email: chay <lichenyi_2020@qq.com>
Project-URL: Homepage, https://github.com/lichenyichay/Unit-Converter
Project-URL: Issues, https://github.com/lichenyichay/Unit-Converter/issues
Classifier: Programming Language :: Python :: 3
Classifier: License :: OSI Approved :: MIT License
Classifier: Operating System :: OS Independent
Requires-Python: >=3.5
License-File: LICENSE
